apikeystore/__init__.py
apikeystore/__version__.py
apikeystore/authentication.py
apikeystore/vaults.py
apikeystore-0.0.10.dist-info/METADATA
apikeystore-0.0.10.dist-info/WHEEL
apikeystore-0.0.10.dist-info/top_level.txt
apikeystore-0.0.10.dist-info/RECORD
