Metadata-Version: 2.1
Name: apikeystore
Version: 0.0.10
Summary: UNKNOWN
Home-page: https://bitbucket.org/ewright3/apikeystore/
Author: Eugene Wright
Author-email: eugene@ewright3.com
License: MIT
Platform: UNKNOWN
Classifier: Programming Language :: Python :: 3
Classifier: License :: OSI Approved :: MIT License
Classifier: Operating System :: OS Independent
Classifier: Development Status :: 2 - Pre-Alpha
